poetry_babel_plugin/__init__.py
poetry_babel_plugin/plugin.py
poetry_babel_plugin-0.2.1.dist-info/LICENSE
poetry_babel_plugin-0.2.1.dist-info/METADATA
poetry_babel_plugin-0.2.1.dist-info/WHEEL
poetry_babel_plugin-0.2.1.dist-info/entry_points.txt
poetry_babel_plugin-0.2.1.dist-info/RECORD
